nova/__init__.py
nova/galaxy/__init__.py
nova/galaxy/connection.py
nova/galaxy/data_store.py
nova/galaxy/dataset.py
nova/galaxy/interfaces.py
nova/galaxy/job.py
nova/galaxy/outputs.py
nova/galaxy/parameters.py
nova/galaxy/tool.py
nova/galaxy/tool_runner.py
nova/galaxy/workflow.py
nova_galaxy-0.11.6.dist-info/METADATA
nova_galaxy-0.11.6.dist-info/WHEEL
nova_galaxy-0.11.6.dist-info/licenses/LICENSE
nova_galaxy-0.11.6.dist-info/RECORD
