Metadata-Version: 2.4
Name: nova-galaxy
Version: 0.11.6
Summary: Utilties for accessing the ORNL Galaxy instance
Author-email: Greg Watson <watsongr@ornl.gov>, Gregory Cage <cagege@ornl.gov>, Sergey Yakubov <yakubovs@ornl.gov>
License-Expression: MIT
License-File: LICENSE
Keywords: Galaxy,NOVA,python
Requires-Python: <3.14,>=3.10
Requires-Dist: bioblend>=1.5.0
Requires-Dist: blinker>=1.9.0
Requires-Dist: deprecated>=1.2.18
Requires-Dist: nova-common>=0.2.0
Requires-Dist: tomli>=2.0.2
